japhrase/__init__.py
japhrase/checker.py
japhrase/cli.py
japhrase/comparison_analyzer.py
japhrase/config.py
japhrase/constants.py
japhrase/cooccurrence.py
japhrase/datasource.py
japhrase/evaluation.py
japhrase/extracter.py
japhrase/optimization.py
japhrase/patterns.py
japhrase/segmenter.py
japhrase/similarity.py
japhrase/summarizer.py
japhrase/use_cases.py
japhrase/utils.py
japhrase/workflow.py
japhrase/writing_assistant.py
japhrase/writing_tools.py
japhrase-0.2.0.dist-info/licenses/LICENSE
japhrase-0.2.0.dist-info/METADATA
japhrase-0.2.0.dist-info/WHEEL
japhrase-0.2.0.dist-info/entry_points.txt
japhrase-0.2.0.dist-info/top_level.txt
japhrase-0.2.0.dist-info/RECORD
