Metadata-Version: 2.4
Name: japhrase
Version: 0.2.0
Summary: Advanced Japanese phrase extraction engine with statistical analysis (PMI/Entropy), text summarization, and writing assistance tools
Author-email: Takeshi SHIMIZU <shim1zu@hotmail.com>
Maintainer-email: Takeshi SHIMIZU <shim1zu@hotmail.com>
License: MIT
Project-URL: Homepage, https://github.com/tshim1zu/phrase-project
Project-URL: Repository, https://github.com/tshim1zu/phrase-project
Project-URL: Documentation, https://github.com/tshim1zu/phrase-project#readme
Project-URL: Bug Tracker, https://github.com/tshim1zu/phrase-project/issues
Keywords: nlp,japanese,phrase-extraction,text-analysis,japanese-nlp
Classifier: Development Status :: 4 - Beta
Classifier: Environment :: Console
Classifier: Intended Audience :: Developers
Classifier: Intended Audience :: Science/Research
Classifier: License :: OSI Approved :: MIT License
Classifier: Operating System :: OS Independent
Classifier: Programming Language :: Python
Classifier: Programming Language :: Python :: 3
Classifier: Programming Language :: Python :: 3.8
Classifier: Programming Language :: Python :: 3.9
Classifier: Programming Language :: Python :: 3.10
Classifier: Programming Language :: Python :: 3.11
Classifier: Programming Language :: Python :: 3.12
Classifier: Topic :: Software Development :: Libraries :: Python Modules
Classifier: Topic :: Text Processing
Classifier: Topic :: Text Processing :: Linguistic
Classifier: Topic :: Scientific/Engineering :: Information Analysis
Requires-Python: >=3.8
License-File: LICENSE
Requires-Dist: numpy<2.0,>=1.20.0
Requires-Dist: pandas<3.0,>=1.3.0
Requires-Dist: openpyxl>=3.0.0
Requires-Dist: chardet>=4.0.0
Requires-Dist: click>=8.0.0
Requires-Dist: PyYAML>=6.0
Requires-Dist: networkx>=2.6
Requires-Dist: python-Levenshtein>=0.12.0
Provides-Extra: dev
Requires-Dist: pytest>=6.0.0; extra == "dev"
Requires-Dist: pytest-cov>=2.0.0; extra == "dev"
Requires-Dist: black>=21.0; extra == "dev"
Requires-Dist: flake8>=3.9.0; extra == "dev"
Requires-Dist: mypy>=0.910; extra == "dev"
Requires-Dist: optuna>=3.0.0; extra == "dev"
Provides-Extra: similarity
Requires-Dist: scikit-learn>=0.24.0; extra == "similarity"
Requires-Dist: matplotlib>=3.3.0; extra == "similarity"
Requires-Dist: seaborn>=0.11.0; extra == "similarity"
Provides-Extra: notebook
Requires-Dist: ipython>=7.0.0; extra == "notebook"
Requires-Dist: jupyter>=1.0.0; extra == "notebook"
Provides-Extra: all
Requires-Dist: pytest>=6.0.0; extra == "all"
Requires-Dist: pytest-cov>=2.0.0; extra == "all"
Requires-Dist: black>=21.0; extra == "all"
Requires-Dist: flake8>=3.9.0; extra == "all"
Requires-Dist: mypy>=0.910; extra == "all"
Requires-Dist: scikit-learn>=0.24.0; extra == "all"
Requires-Dist: matplotlib>=3.3.0; extra == "all"
Requires-Dist: seaborn>=0.11.0; extra == "all"
Requires-Dist: ipython>=7.0.0; extra == "all"
Requires-Dist: jupyter>=1.0.0; extra == "all"
Dynamic: license-file
